encrypt256/__init__.py
encrypt256-1.8.6.2.dist-info/LICENSE
encrypt256-1.8.6.2.dist-info/WHEEL
encrypt256-1.8.6.2.dist-info/METADATA
encrypt256-1.8.6.2.dist-info/RECORD
