Metadata-Version: 2.1
Name: encrypt256
Version: 1.8.6.2
Summary: str 型和 bytes 型数据加密器
Keywords: encrypt256,encrypt,AES,pycryptodome,Crypto
Author-email: "lcctoor.com" <lcctoor@outlook.com>
Classifier: License :: OSI Approved :: Apache Software License
Requires-Dist: arts
Project-URL: HomePage, https://github.com/lcctoor/arts/tree/main/arts/encrypt256
